fullcolor/__init__.py
fullcolor/colors.py
fullcolor/common.py
fullcolor/fullcolor.py
fullcolor-0.2.4.dist-info/DESCRIPTION.rst
fullcolor-0.2.4.dist-info/METADATA
fullcolor-0.2.4.dist-info/RECORD
fullcolor-0.2.4.dist-info/WHEEL
fullcolor-0.2.4.dist-info/metadata.json
fullcolor-0.2.4.dist-info/top_level.txt
