Metadata-Version: 2.0
Name: fullcolor
Version: 0.2.4
Summary: Provides an easy way to print full 24bit colors in terminals (those that support it).
Home-page: https://github.com/eternali/fullcolor
Author: Conrad Heidebrecht
Author-email: conrad.heidebrecht@gmail.com
License: UNKNOWN
Keywords: color colour terminal logging
Platform: linux
Classifier: Development Status :: 4 - Beta
Classifier: Intended Audience :: Developers
Classifier: License :: OSI Approved :: GNU General Public License v3 or later (GPLv3+)
Classifier: Programming Language :: Python :: 2
Classifier: Programming Language :: Python :: 3
